Workbook
Name Archivo: Archivo!$A$2:$B$6
Name fincas: Fincas!$A$3:$B$10
Name Lista: #REF!
Name lista_labores: Lista_Labores!$A$2:$D$1588
Name lista_trabaja: lista_trabajadores!$A$2:$D$261
Name usuarios: #REF!

Sheet RDT
B2: Reporte Diario TRAVECEDO | K2: Coordinador:
B4: Cód. Agrosoft | K4: Administrador:
B5: Nombre Finca | D5: =IF(D4<>"",VLOOKUP(D4,Archivo!A:B,2,FALSE),"")
B6: Periodo Pago | K6: Aprobado:
B7: Fecha RDTs AAAAMMDD | E7: Documento | J7: PROCESADO
B8: Año | G8: Campos
B9: semana | G9: obligatorios
O10: 1 | S10: 2 | W10: 3 | AA10: 4 | AD10: 5 | AG10: 6 | AJ10: 7 | AM10: 8 | AP10: 9
B11: Fecha | C11: Código Trabajador | D11: Nombre del Trabajador | G11: Horas Jornada | H11: Horas Labor | I11: Cod. Finca Laboro | J11: Código Labor | K11: Nombre Labor | L11: Unidades a pagar | M11: Vr. Undidad | N11: Porcentaje Recargo | O11: Lote Nro | P11: Area Lote | Q11: Sem Normal | R11: Sem Atrazo | S11: Lote Nro | T11: Area Lote | U11: Sem Normal | V11: Sem Atrazo | W11: Lote Nro | X11: Area Lote | Y11: Sem Normal | Z11: Semanas Atrazo | AA11: Lote Nro | AB11: Area Lote | AC11: Semanas Atrazo | AD11: Lote Nro | AE11: Area Lote | AF11: Semanas Atrazo | AG11: Lote Nro | AH11: Area Lote | AI11: Semanas Atrazo | AJ11: Lote Nro | AK11: Area Lote | AL11: Semanas Atrazo | AM11: Lote Nro | AN11: Area Lote | AO11: Semanas Atrazo | AP11: Lote Nro | AQ11: Area Lote | AR11: Sem Normal | AS11: Semanas Atrazo | AT11: Observaciones | AU11: TOTAL | AW11: Precio | AX11: Valor Dia | AZ11: Cajas elaboradas | BB11: 480 | BC11: Catorcena | BD11: Fecha | BF11: OBSERVACIONES
AZ12: Corte caja integral | BA12: =COUNTIF($K$13:$K$1048576,$AZ12)+COUNTIF($K$13:$K$1048576,"Corte caja integral festivo")+COUNTIF($K$13:$K$1048576,"Corte caja integral dominical") | BB12: =SUMIF($K$13:$K$1048576,$AZ12,$L$13:$L$1048576)+SUMIF($K$13:$K$1048576,"Corte caja integral festivo",$L$13:$L$1048576)+SUMIF($K$13:$K$1048576,"Corte caja integral dominical",$L$13:$L$1048576)
C13: =IFERROR(VLOOKUP(D13,lista_trabajadores!B:E,4,FALSE),"") | J13: =IFERROR(VLOOKUP($K13,Tabla1[[NOMBRE]:[CODIGO2]],4,0),"") | L13: =SUMIF($O$11:$AB$11,"Area Lote",$O13:$AB13) | AW13: =IF(J13<>" ",VLOOKUP(J13,lista_labores,4,FALSE)," ") | AX13: =+AW13*L13 | AZ13: Corte promedio | BA13: =COUNTIF($K$13:$K$1048576,$AZ13)+COUNTIF($K$13:$K$1048576,"Corte promedio festivo")+COUNTIF($K$13:$K$1048576,"Corte promedio dominical") | BB13: =SUMIF($K$13:$K$1048576,$AZ13,$L$13:$L$1048576)+SUMIF($K$13:$K$1048576,"Corte promedio festivo",$L$13:$L$1048576)+SUMIF($K$13:$K$1048576,"Corte promedio dominical",$L$13:$L$1048576)
C14: =IFERROR(VLOOKUP(D14,lista_trabajadores!B:E,4,FALSE),"") | J14: =IFERROR(VLOOKUP($K14,Tabla1[[NOMBRE]:[CODIGO2]],4,0),"") | L14: =SUMIF($O$11:$AB$11,"Area Lote",$O14:$AB14) | AW14: =IF(J14<>" ",VLOOKUP(J14,lista_labores,4,FALSE)," ") | AX14: =+AW14*L14 | AZ14: Corte promedio rechazo | BA14: =COUNTIF($K$13:$K$1048576,$AZ14)+COUNTIF($K$13:$K$1048576,"Corte promedio rechazo festivo")+COUNTIF($K$13:$K$1048576,"Corte promedio rechazo dominical") | BB14: =SUMIF($K$13:$K$1048576,$AZ14,$L$13:$L$1048576)+SUMIF($K$13:$K$1048576,"Corte promedio rechazo festivo",$L$13:$L$1048576)+SUMIF($K$13:$K$1048576,"Corte promedio rechazo dominical",$L$13:$L$1048576)
C15: =IFERROR(VLOOKUP(D15,lista_trabajadores!B:E,4,FALSE),"") | J15: =IFERROR(VLOOKUP($K15,Tabla1[[NOMBRE]:[CODIGO2]],4,0),"") | L15: =SUMIF($O$11:$AB$11,"Area Lote",$O15:$AB15) | AW15: =IF(J15<>" ",VLOOKUP(J15,lista_labores,4,FALSE)," ") | AX15: =+AW15*L15 | AZ15: Corte promedio bioseguridad | BA15: =COUNTIF($K$13:$K$1048576,$AZ15)+COUNTIF($K$13:$K$1048576,"Corte promedio bioseguridad festivo")+COUNTIF($K$13:$K$1048576,"Corte promedio bioseguridad dominical") | BB15: =SUMIF($K$13:$K$1048576,$AZ15,$L$13:$L$1048576)+SUMIF($K$13:$K$1048576,"Corte promedio bioseguridad festivo",$L$13:$L$1048576)+SUMIF($K$13:$K$1048576,"Corte promedio bioseguridad dominical",$L$13:$L$1048576)
C16: =IFERROR(VLOOKUP(D16,lista_trabajadores!B:E,4,FALSE),"") | J16: =IFERROR(VLOOKUP($K16,Tabla1[[NOMBRE]:[CODIGO2]],4,0),"") | L16: =SUMIF($O$11:$AB$11,"Area Lote",$O16:$AB16) | AW16: =IF(J16<>" ",VLOOKUP(J16,lista_labores,4,FALSE)," ") | AX16: =+AW16*L16 | AZ16: Corte promedio cablero | BA16: =COUNTIF($K$13:$K$1048576,$AZ16)+COUNTIF($K$13:$K$1048576,"Corte promedio cablero festivo")+COUNTIF($K$13:$K$1048576,"Corte promedio cablero dominical") | BB16: =SUMIF($K$13:$K$1048576,$AZ16,$L$13:$L$1048576)+SUMIF($K$13:$K$1048576,"Corte promedio cablero festivo",$L$13:$L$1048576)+SUMIF($K$13:$K$1048576,"Corte promedio cablero dominical",$L$13:$L$1048576)
C17: =IFERROR(VLOOKUP(D17,lista_trabajadores!B:E,4,FALSE),"") | J17: =IFERROR(VLOOKUP($K17,Tabla1[[NOMBRE]:[CODIGO2]],4,0),"") | L17: =SUMIF($O$11:$AB$11,"Area Lote",$O17:$AB17) | AW17: =IF(J17<>" ",VLOOKUP(J17,lista_labores,4,FALSE)," ") | AX17: =+AW17*L17 | BB17: =BB11-BB12
C18: =IFERROR(VLOOKUP(D18,lista_trabajadores!B:E,4,FALSE),"") | J18: =IFERROR(VLOOKUP($K18,Tabla1[[NOMBRE]:[CODIGO2]],4,0),"") | L18: =SUMIF($O$11:$AB$11,"Area Lote",$O18:$AB18) | AW18: =IF(J18<>" ",VLOOKUP(J18,lista_labores,4,FALSE)," ") | AX18: =+AW18*L18
C19: =IFERROR(VLOOKUP(D19,lista_trabajadores!B:E,4,FALSE),"") | J19: =IFERROR(VLOOKUP($K19,Tabla1[[NOMBRE]:[CODIGO2]],4,0),"") | L19: =SUMIF($O$11:$AB$11,"Area Lote",$O19:$AB19) | AW19: =IF(J19<>" ",VLOOKUP(J19,lista_labores,4,FALSE)," ") | AX19: =+AW19*L19
C20: =IFERROR(VLOOKUP(D20,lista_trabajadores!B:E,4,FALSE),"") | J20: =IFERROR(VLOOKUP($K20,Tabla1[[NOMBRE]:[CODIGO2]],4,0),"") | L20: =SUMIF($O$11:$AB$11,"Area Lote",$O20:$AB20) | AW20: =IF(J20<>" ",VLOOKUP(J20,lista_labores,4,FALSE)," ") | AX20: =+AW20*L20
C21: =IFERROR(VLOOKUP(D21,lista_trabajadores!B:E,4,FALSE),"") | J21: =IFERROR(VLOOKUP($K21,Tabla1[[NOMBRE]:[CODIGO2]],4,0),"") | L21: =SUMIF($O$11:$AB$11,"Area Lote",$O21:$AB21) | AW21: =IF(J21<>" ",VLOOKUP(J21,lista_labores,4,FALSE)," ") | AX21: =+AW21*L21
C22: =IFERROR(VLOOKUP(D22,lista_trabajadores!B:E,4,FALSE),"") | J22: =IFERROR(VLOOKUP($K22,Tabla1[[NOMBRE]:[CODIGO2]],4,0),"") | L22: =SUMIF($O$11:$AB$11,"Area Lote",$O22:$AB22) | AW22: =IF(J22<>" ",VLOOKUP(J22,lista_labores,4,FALSE)," ") | AX22: =+AW22*L22
C23: =IFERROR(VLOOKUP(D23,lista_trabajadores!B:E,4,FALSE),"") | J23: =IFERROR(VLOOKUP($K23,Tabla1[[NOMBRE]:[CODIGO2]],4,0),"") | L23: =SUMIF($O$11:$AB$11,"Area Lote",$O23:$AB23) | AW23: =IF(J23<>" ",VLOOKUP(J23,lista_labores,4,FALSE)," ") | AX23: =+AW23*L23
C24: =IFERROR(VLOOKUP(D24,lista_trabajadores!B:E,4,FALSE),"") | J24: =IFERROR(VLOOKUP($K24,Tabla1[[NOMBRE]:[CODIGO2]],4,0),"") | L24: =SUMIF($O$11:$AB$11,"Area Lote",$O24:$AB24) | AW24: =IF(J24<>" ",VLOOKUP(J24,lista_labores,4,FALSE)," ") | AX24: =+AW24*L24
C25: =IFERROR(VLOOKUP(D25,lista_trabajadores!B:E,4,FALSE),"") | J25: =IFERROR(VLOOKUP($K25,Tabla1[[NOMBRE]:[CODIGO2]],4,0),"") | L25: =SUMIF($O$11:$AB$11,"Area Lote",$O25:$AB25) | AW25: =IF(J25<>" ",VLOOKUP(J25,lista_labores,4,FALSE)," ") | AX25: =+AW25*L25
C26: =IFERROR(VLOOKUP(D26,lista_trabajadores!B:E,4,FALSE),"") | J26: =IFERROR(VLOOKUP($K26,Tabla1[[NOMBRE]:[CODIGO2]],4,0),"") | L26: =SUMIF($O$11:$AB$11,"Area Lote",$O26:$AB26) | AW26: =IF(J26<>" ",VLOOKUP(J26,lista_labores,4,FALSE)," ") | AX26: =+AW26*L26
C27: =IFERROR(VLOOKUP(D27,lista_trabajadores!B:E,4,FALSE),"") | J27: =IFERROR(VLOOKUP($K27,Tabla1[[NOMBRE]:[CODIGO2]],4,0),"") | L27: =SUMIF($O$11:$AB$11,"Area Lote",$O27:$AB27) | AW27: =IF(J27<>" ",VLOOKUP(J27,lista_labores,4,FALSE)," ") | AX27: =+AW27*L27
C28: =IFERROR(VLOOKUP(D28,lista_trabajadores!B:E,4,FALSE),"") | J28: =IFERROR(VLOOKUP($K28,Tabla1[[NOMBRE]:[CODIGO2]],4,0),"") | L28: =SUMIF($O$11:$AB$11,"Area Lote",$O28:$AB28) | AW28: =IF(J28<>" ",VLOOKUP(J28,lista_labores,4,FALSE)," ") | AX28: =+AW28*L28
C29: =IFERROR(VLOOKUP(D29,lista_trabajadores!B:E,4,FALSE),"") | J29: =IFERROR(VLOOKUP($K29,Tabla1[[NOMBRE]:[CODIGO2]],4,0),"") | L29: =SUMIF($O$11:$AB$11,"Area Lote",$O29:$AB29) | AW29: =IF(J29<>" ",VLOOKUP(J29,lista_labores,4,FALSE)," ") | AX29: =+AW29*L29
... C120: =IFERROR(VLOOKUP(D120,lista_trabajadores!B:E,4,FALSE),"") | J120: =IFERROR(VLOOKUP($K120,Tabla1[[NOMBRE]:[CODIGO2]],4,0),"") | L120: =SUMIF($O$11:$AB$11,"Area Lote",$O120:$AB120) | AW120: =IF(J120<>" ",VLOOKUP(J120,lista_labores,4,FALSE)," ") | AX120: =+AW120*L120

Sheet Lista_Labores
A1: CODIGO | B1: NOMBRE | C1: UND | D1: PRECIO | E1: CODIGO2 | H1: REGRESAR A REPORTES
A2: 1 | B2: Administrador | C2: hora | E2: 1
A3: 2 | B3: Coordinador La Alegria | C3: hora | E3: 2
A4: 3 | B4: Coordinador general | C4: hora | E4: 3 | H4: REGRESA
A5: 4 | B5: Colocacion de daipa | C5: unidad | E5: 4
A6: 5 | B6: Desmache con palin | C6: hectarea | E6: 5
A7: 6 | B7: Saldo pendiente dominical promediado | C7: hora | E7: 6
A8: 7 | B8: Inventario de fruta | C8: racimo | E8: 7
A9: 8 | B9: Desague en plantacion | C9: racimo | E9: 8
A10: 9 | B10: Embolse Elizabeth cristina | C10: hora | E10: 9
A11: 10 | B11: Gerente general | C11: hora | E11: 10
A12: 11 | B12: Saldo pendiente fertilizacion | C12: unidad | E12: 11
A13: 12 | B13: Saldo pendiente fumigacion | C13: hora | E13: 12
A14: 13 | B14: Limpia de cerca Elizabeth | C14: mts | E14: 13
A15: 14 | B15: Hechura de cerca Elizabeth | C15: hora | E15: 14
A16: 15 | B16: Fumigacion carola | C16: hora | E16: 15
... A1317: 500206 | B1317: Hechura de trinchera | C1317: hora | E1317: 500206
A1318: 500207 | B1318: Supervisor finca La Alegria | E1318: 500207
A1319: 500208 | B1319: Inventario de carton | C1319: hora | E1319: 500208
A1320: 500209 | B1320: Estaquillada | C1320: hora | E1320: 500209
A1321: 500210 | B1321: Chapia de canal al dia | C1321: hora | E1321: 500210
A1322: 500211 | B1322: Transporte de frutas | C1322: unidad | E1322: 500211
A1323: 500212 | B1323: Transporte a las flores (tanques) | C1323: unidad | E1323: 500212
A1324: 500213 | B1324: Transp materiales empacadora | C1324: hora | E1324: 500213
A1325: 500214 | B1325: Tranporte a las flores carton | C1325: unidad | E1325: 500214
A1326: 500215 | B1326: Acarreo de fertilizante | C1326: hora | E1326: 500215
A1327: 500216 | B1327: Pintura de tuberia y aseo bodega | C1327: hora | E1327: 500216
A1328: 500217 | B1328: Aplicacion de herbicida El Refugio por hora | C1328: hora | E1328: 500217
A1329: 500218 | B1329: Alineacion para siembra | C1329: hora | E1329: 500218
A1330: 500219 | B1330: Limpia de linderos | C1330: metro | E1330: 500219
... A1588: 1266 | B1588: Yumbolon por hectarea | C1588: hectarea | E1588: 1266

Sheet lista_trabajadores
A1: CODIGO | B1: Columna1 | C1: DESCRIPCION | D1: finca | E1: CODIGO2 | F1: tipo | I1: REGRESAR A REPORTES

Sheet Fincas
A2: cod | B2: nombre

Sheet Archivo
A2: cod | B2: Nombre
A3: 01 | B3: LA ALEGRIA
A4: 03 | B4: MARIA LAURA
A5: 04 | B5: EL REFUGIO
A6: 06 | B6: DON GASPAR
A7: 07 | B7: PALMAWA
A8: 20 | B8: MAROMA
